MANIFEST.in
README.md
requirements.txt
setup.py
./search_listview/__init__.py
./search_listview/forms.py
./search_listview/list.py
./search_listview/urls.py
./search_listview/wsgi.py
django_search_listview.egg-info/PKG-INFO
django_search_listview.egg-info/SOURCES.txt
django_search_listview.egg-info/dependency_links.txt
django_search_listview.egg-info/top_level.txt
search_listview/__init__.py
search_listview/forms.py
search_listview/list.py
search_listview/urls.py
search_listview/wsgi.py
search_listview/static/search_listview/js/search_listview.js
search_listview/templates/search_listview/pagination.html
search_listview/templates/search_listview/search_and_page.html
search_listview/templates/search_listview/search_box.html