Metadata-Version: 1.1
Name: django-search-listview
Version: 0.2.1
Summary: Searchable and paginable ListView
Home-page: https://github.com/SchroterQuentin/django-search-listview
Author: Quentin Schroter
Author-email: qschroter@gmail.com
License: PSF
Download-URL: https://github.com/SchroterQuentin/django-search-listview/tarball/0.1
Keywords: django,listView,search
Platform: UNKNOWN
